YFenzhongXuexiXZhongYuyan/README.md
YFenzhongXuexiXZhongYuyan/__init__.py
YFenzhongXuexiXZhongYuyan/__main__.py
YFenzhongXuexiXZhongYuyan/file.epub
YFenzhongXuexiXZhongYuyan/index.html
YFenzhongXuexiXZhongYuyan/css/__init__.py
YFenzhongXuexiXZhongYuyan/css/annotations.css
YFenzhongXuexiXZhongYuyan/css/main.css
YFenzhongXuexiXZhongYuyan/css/normalize.css
YFenzhongXuexiXZhongYuyan/css/popup.css
YFenzhongXuexiXZhongYuyan/font/__init__.py
YFenzhongXuexiXZhongYuyan/font/fontello.eot
YFenzhongXuexiXZhongYuyan/font/fontello.svg
YFenzhongXuexiXZhongYuyan/font/fontello.ttf
YFenzhongXuexiXZhongYuyan/font/fontello.woff
YFenzhongXuexiXZhongYuyan/img/__init__.py
YFenzhongXuexiXZhongYuyan/img/annotator-glyph-sprite.png
YFenzhongXuexiXZhongYuyan/img/annotator-icon-sprite.png
YFenzhongXuexiXZhongYuyan/img/apple-touch-icon.png
YFenzhongXuexiXZhongYuyan/img/cancelfullscreen.png
YFenzhongXuexiXZhongYuyan/img/close.png
YFenzhongXuexiXZhongYuyan/img/fullscreen.png
YFenzhongXuexiXZhongYuyan/img/loader.gif
YFenzhongXuexiXZhongYuyan/img/menu-icon.png
YFenzhongXuexiXZhongYuyan/img/save.png
YFenzhongXuexiXZhongYuyan/img/saved.png
YFenzhongXuexiXZhongYuyan/img/settings-s.png
YFenzhongXuexiXZhongYuyan/img/settings.png
YFenzhongXuexiXZhongYuyan/img/star.png
YFenzhongXuexiXZhongYuyan/js/__init__.py
YFenzhongXuexiXZhongYuyan/js/epub.js
YFenzhongXuexiXZhongYuyan/js/epub.min.js
YFenzhongXuexiXZhongYuyan/js/epub.min.map
YFenzhongXuexiXZhongYuyan/js/hooks.min.js
YFenzhongXuexiXZhongYuyan/js/hooks.min.map
YFenzhongXuexiXZhongYuyan/js/reader.js
YFenzhongXuexiXZhongYuyan/js/reader.js.map
YFenzhongXuexiXZhongYuyan/js/reader.min.js
YFenzhongXuexiXZhongYuyan/js/reader.min.map
YFenzhongXuexiXZhongYuyan/js/hooks/__init__.py
YFenzhongXuexiXZhongYuyan/js/hooks/extensions/__init__.py
YFenzhongXuexiXZhongYuyan/js/hooks/extensions/highlight.js
YFenzhongXuexiXZhongYuyan/js/libs/__init__.py
YFenzhongXuexiXZhongYuyan/js/libs/jquery.min.js
YFenzhongXuexiXZhongYuyan/js/libs/localforage.min.js
y_fenzhong_xuexi_x_zhong_yuyan-2024.3.2.0.dist-info/METADATA
y_fenzhong_xuexi_x_zhong_yuyan-2024.3.2.0.dist-info/WHEEL
y_fenzhong_xuexi_x_zhong_yuyan-2024.3.2.0.dist-info/entry_points.txt
y_fenzhong_xuexi_x_zhong_yuyan-2024.3.2.0.dist-info/top_level.txt
y_fenzhong_xuexi_x_zhong_yuyan-2024.3.2.0.dist-info/RECORD
